{"cameraMode":{"drawMode":0,"name":"Shaded","section":"Shading Mode"},"sceneLighting":false,"audioPlay":false,"sceneViewState":{"m_AlwaysRefresh":false,"showFog":false,"showSkybox":false,"showFlares":false,"showImageEffects":false,"showParticleSystems":true,"showVisualEffectGraphs":true,"m_FxEnabled":true},"in2DMode":false,"pivot":{"x":22.270015716552736,"y":61.432403564453128,"z":-0.22028207778930665},"rotation":{"x":-0.005375701934099197,"y":0.9917042255401611,"z":-0.11838529258966446,"w":-0.04559500887989998},"size":5.337718963623047,"orthographic":false}